pyconn/__init__.py
pyconn/connector.py
pyconn/database.py
pyconn/explorer.py
pyconn/file.py
pyconn/ftp.py
pyconn/util.py
pyqconn/__init__.py
pyqconn/connector.py
pyqconn/database.py
pyqconn/explorer.py
pyqconn/file.py
pyqconn/ftp.py
pyqconn/util.py
pyqconn-0.1.dist-info/METADATA
pyqconn-0.1.dist-info/WHEEL
pyqconn-0.1.dist-info/top_level.txt
pyqconn-0.1.dist-info/RECORD
