Metadata-Version: 2.1
Name: pyqconn
Version: 0.1
Summary: to use various protocols and connections with same interface.
Home-page: https://https://github.com/adghk0/pyqconn
Author: Eom Kyoungjun
Author-email: kj@ekj.kr
License: UNKNOWN
Platform: UNKNOWN
Classifier: Programming Language :: Python :: 3.7
Classifier: License :: OSI Approved :: MIT License
Classifier: Operating System :: OS Independent
Requires-Python: >=3.7
